README
setup.py
jsonConfig/__init__.py
jsonConfig/config.py
jsonConfig/constants.py
jsonConfig/editor.py
jsonConfig/odict.py
jsonConfig.egg-info/PKG-INFO
jsonConfig.egg-info/SOURCES.txt
jsonConfig.egg-info/dependency_links.txt
jsonConfig.egg-info/top_level.txt