Metadata-Version: 1.0
Name: jsonConfig
Version: 0.1.1
Summary: Sparse JSON based config files with GUI editor.
Home-page: https://github.com/RyanHope/jsonConfig
Author: Ryan Hope
Author-email: rmh3093@gmail.com
License: GPL-3
Platform: UNKNOWN
Classifier: License :: OSI Approved :: GNU General Public License (GPL)
Classifier: Programming Language :: Python :: 2
Classifier: Topic :: Utilities
